pal_rcon-0.0.3.dist-info/METADATA
pal_rcon-0.0.3.dist-info/WHEEL
pal_rcon-0.0.3.dist-info/licenses/LICENSE
pal_rcon/__init__.py
pal_rcon/__main__.py
pal_rcon/async_pal_rcon.py
pal_rcon/cli.py
pal_rcon/errors.py
pal_rcon/models.py
pal_rcon/pal_rcon.py
pal_rcon/utils.py
pal_rcon-0.0.3.dist-info/RECORD
