Metadata-Version: 2.1
Name: pal_rcon
Version: 0.0.3
Summary: Rcon client dedicated to Palworld that supports both sync and async
Home-page: https://github.com/Charahiro-tan/pal_rcon
Author-Email: Charahiro-tan <charahiro.tan@gmail.com>
License: MIT
Classifier: License :: OSI Approved :: MIT License
Classifier: Natural Language :: Japanese
Classifier: Programming Language :: Python :: 3
Project-URL: Homepage, https://github.com/Charahiro-tan/pal_rcon
Requires-Python: >=3.10
